{
  "headline": "Clear today, storms Monday — water new beds now",
  "weather_notes": [
    "Today is dry at 78°F (2% precip) — the only reliable outdoor window before Monday's 50% afternoon storm risk.",
    "Monday–Tuesday carry 50–52% precip chances; if storms miss, newly sown w1 and w4 won't get enough natural moisture to skip irrigation.",
    "If Monday–Tuesday rain does land, hold irrigation and check bed moisture Wednesday before watering again.",
    "Tuesday night low 42°F — no frost risk for any active planting this week."
  ],
  "surfaced_tasks": [],
  "suggested_tasks": [
    {
      "title": "Water strawberry and onion beds before storms",
      "due_date": "2026-05-03",
      "description": "Two days since last irrigation and 78°F today — water w1 and w4 now since Monday's 50% storm chance isn't guaranteed to deliver enough moisture for newly sown beds.",
      "bed_id": "w1",
      "urgency": "normal"
    }
  ]
}
